pyramid_beaker/__init__.py
pyramid_beaker/tests.py
pyramid_beaker-0.9.dist-info/LICENSE.txt
pyramid_beaker-0.9.dist-info/METADATA
pyramid_beaker-0.9.dist-info/WHEEL
pyramid_beaker-0.9.dist-info/top_level.txt
pyramid_beaker-0.9.dist-info/RECORD
