Metadata-Version: 2.1
Name: pyramid_beaker
Version: 0.9
Summary: Beaker session factory backend for Pyramid
Home-page: https://docs.pylonsproject.org/projects/pyramid_beaker/en/latest/
Author: Chris McDonough, Agendaless Consulting
Author-email: pylons-discuss@googlegroups.com
License: BSD-derived (http://www.repoze.org/LICENSE.txt)
Keywords: web wsgi pylons pyramid
Classifier: Intended Audience :: Developers
Classifier: Programming Language :: Python
Classifier: Programming Language :: Python :: 2
Classifier: Programming Language :: Python :: 2.7
Classifier: Programming Language :: Python :: 3
Classifier: Programming Language :: Python :: 3.7
Classifier: Programming Language :: Python :: 3.8
Classifier: Programming Language :: Python :: 3.9
Classifier: Programming Language :: Python :: 3.10
Classifier: Programming Language :: Python :: 3.11
Classifier: Programming Language :: Python :: 3.12
Classifier: Programming Language :: Python :: Implementation :: CPython
Classifier: Programming Language :: Python :: Implementation :: PyPy
Classifier: Framework :: Pyramid
License-File: LICENSE.txt
Requires-Dist: pyramid
Requires-Dist: beaker
Provides-Extra: docs
Requires-Dist: Sphinx ; extra == 'docs'
Requires-Dist: docutils ; extra == 'docs'
Requires-Dist: pylons-sphinx-themes ; extra == 'docs'
Provides-Extra: testing
Requires-Dist: nose ; extra == 'testing'
Requires-Dist: coverage ; extra == 'testing'
